scietex/hal/vacuum_gauge/__init__.py
scietex/hal/vacuum_gauge/py.typed
scietex/hal/vacuum_gauge/version.py
scietex/hal/vacuum_gauge/base/__init__.py
scietex/hal/vacuum_gauge/base/analog.py
scietex/hal/vacuum_gauge/base/atmosphere.py
scietex/hal/vacuum_gauge/edwards/__init__.py
scietex/hal/vacuum_gauge/edwards/analog.py
scietex/hal/vacuum_gauge/edwards/calibration_data.py
scietex/hal/vacuum_gauge/erstevak/__init__.py
scietex/hal/vacuum_gauge/erstevak/analog.py
scietex/hal/vacuum_gauge/erstevak/rs485/__init__.py
scietex/hal/vacuum_gauge/erstevak/rs485/v1/__init__.py
scietex/hal/vacuum_gauge/erstevak/rs485/v1/client.py
scietex/hal/vacuum_gauge/erstevak/rs485/v1/emulation.py
scietex/hal/vacuum_gauge/erstevak/rs485/v2/__init__.py
scietex/hal/vacuum_gauge/erstevak/rs485/v2/client.py
scietex/hal/vacuum_gauge/leybold/__init__.py
scietex/hal/vacuum_gauge/leybold/analog.py
scietex/hal/vacuum_gauge/thyracont/__init__.py
scietex/hal/vacuum_gauge/thyracont/rs485/__init__.py
scietex/hal/vacuum_gauge/thyracont/rs485/checksum.py
scietex/hal/vacuum_gauge/thyracont/rs485/decoder.py
scietex/hal/vacuum_gauge/thyracont/rs485/framer.py
scietex/hal/vacuum_gauge/thyracont/rs485/v1/__init__.py
scietex/hal/vacuum_gauge/thyracont/rs485/v1/client.py
scietex/hal/vacuum_gauge/thyracont/rs485/v1/data.py
scietex/hal/vacuum_gauge/thyracont/rs485/v1/decoder.py
scietex/hal/vacuum_gauge/thyracont/rs485/v1/emulation.py
scietex/hal/vacuum_gauge/thyracont/rs485/v1/emulation_utils.py
scietex/hal/vacuum_gauge/thyracont/rs485/v1/framer.py
scietex/hal/vacuum_gauge/thyracont/rs485/v1/request.py
scietex/hal/vacuum_gauge/thyracont/rs485/v2/__init__.py
scietex/hal/vacuum_gauge/thyracont/rs485/v2/client.py
scietex/hal/vacuum_gauge/thyracont/rs485/v2/data.py
scietex/hal/vacuum_gauge/thyracont/rs485/v2/decoder.py
scietex/hal/vacuum_gauge/thyracont/rs485/v2/framer.py
scietex/hal/vacuum_gauge/thyracont/rs485/v2/request.py
scietex_hal_vacuum_gauge-1.1.0.dist-info/licenses/LICENSE
scietex_hal_vacuum_gauge-1.1.0.dist-info/METADATA
scietex_hal_vacuum_gauge-1.1.0.dist-info/WHEEL
scietex_hal_vacuum_gauge-1.1.0.dist-info/top_level.txt
scietex_hal_vacuum_gauge-1.1.0.dist-info/RECORD
