Metadata-Version: 2.4
Name: scietex.hal.vacuum_gauge
Version: 1.1.0
Summary: Scietex Vacuum Gauge HAL package
Author-email: Anton Bondarenko <bond.anton@gmail.com>
License: MIT License
Project-URL: Homepage, https://github.com/bond-anton/scietex.hal.vacuum_gauge
Project-URL: Bug Tracker, https://github.com/bond-anton/scietex.hal.vacuum_gauge/issues
Classifier: Programming Language :: Python :: 3
Classifier: License :: OSI Approved :: MIT License
Classifier: Operating System :: OS Independent
Requires-Python: >=3.10
License-File: LICENSE
Requires-Dist: scietex.hal.analog-sensor<2.0.0,>=1.0.0
Requires-Dist: scietex.hal.serial<2.0.0,>=1.1.0
Provides-Extra: dev
Provides-Extra: test
Requires-Dist: flake8; extra == "test"
Requires-Dist: pytest; extra == "test"
Requires-Dist: pytest-asyncio; extra == "test"
Provides-Extra: lint
Requires-Dist: pylint; extra == "lint"
Dynamic: license-file
